scioer/__init__.py
scioer/__version__.py
scioer/cli.py
scioer/docker.py
scioer/config/__init__.py
scioer/config/load.py
scioer/config/parse.py
tests/test_cli.py
sci_oer-1.3.0.dist-info/LICENSE
sci_oer-1.3.0.dist-info/METADATA
sci_oer-1.3.0.dist-info/WHEEL
sci_oer-1.3.0.dist-info/entry_points.txt
sci_oer-1.3.0.dist-info/top_level.txt
sci_oer-1.3.0.dist-info/RECORD
