Metadata-Version: 2.1
Name: sci-oer
Version: 1.3.0
Summary: A cli application to help launch the sci-oer course container
Author-email: Marshall Asch <masch@uoguelph.ca>
Project-URL: Documentation, https://github.com/sci-oer/student-cli/blob/main/README.md
Project-URL: Source, https://github.com/sci-oer/student-cli
Project-URL: Bug Tracker, https://github.com/sci-oer/student-cli/issues
Project-URL: Funding, https://github.com/sci-oer/student-cli/blob/main/.github/FUNDING.md
Classifier: Development Status :: 5 - Production/Stable
Classifier: Intended Audience :: Education
Classifier: Intended Audience :: Developers
Classifier: Programming Language :: Python :: 3.10
Classifier: Programming Language :: Python :: 3.9
Classifier: Programming Language :: Python :: 3.8
Classifier: Programming Language :: Python :: 3.7
Classifier: License :: OSI Approved :: GNU Affero General Public License v3
Classifier: Operating System :: OS Independent
Classifier: Topic :: Education
Classifier: Topic :: Education :: Computer Aided Instruction (CAI)
Classifier: Topic :: Software Development
Classifier: Topic :: Utilities
Requires-Python: >=3.7
License-File: LICENSE
Requires-Dist: PyYAML (==6.0.1)
Requires-Dist: attrs (==23.1.0)
Requires-Dist: click (==8.1.6)
Requires-Dist: colorlog (==6.7.0)
Requires-Dist: docker (==6.1.3)
Requires-Dist: iniconfig (==2.0.0)
Requires-Dist: mypy-extensions (==1.0.0)
Requires-Dist: packaging (==23.1)
Requires-Dist: pathspec (==0.11.1)
Requires-Dist: platformdirs (==3.5.0)
Requires-Dist: pluggy (==1.0.0)
Requires-Dist: py (==1.11.0)
Requires-Dist: pyparsing (==3.1.0)
Requires-Dist: rich (==13.4.2)
Requires-Dist: shellingham (==1.5.1)
Requires-Dist: tomli (==2.0.1)
Requires-Dist: typer (==0.9.0)
Requires-Dist: typing-extensions (==4.7.1)
Requires-Dist: pyreadline3 (==3.4.1) ; platform_system == "Windows"
